pyjwt_key_fetcher/__init__.py
pyjwt_key_fetcher/errors.py
pyjwt_key_fetcher/fetcher.py
pyjwt_key_fetcher/http_client.py
pyjwt_key_fetcher/key.py
pyjwt_key_fetcher/provider.py
pyjwt_key_fetcher/py.typed
pyjwt_key_fetcher/tests/__init__.py
pyjwt_key_fetcher/tests/conftest.py
pyjwt_key_fetcher/tests/test_clients.py
pyjwt_key_fetcher/tests/test_fetcher.py
pyjwt_key_fetcher/tests/test_utils.py
pyjwt_key_fetcher/utils.py
pyjwt_key_fetcher-0.8.0.dist-info/LICENSE
pyjwt_key_fetcher-0.8.0.dist-info/METADATA
pyjwt_key_fetcher-0.8.0.dist-info/WHEEL
pyjwt_key_fetcher-0.8.0.dist-info/RECORD
