Metadata-Version: 2.1
Name: pyjwt-key-fetcher
Version: 0.8.0
Summary: Async library to fetch JWKs for JWT tokens
Home-page: https://github.com/ioxiocom/pyjwt-key-fetcher
License: BSD-3-Clause
Author: IOXIO Ltd
Requires-Python: >=3.8,<4.0
Classifier: License :: OSI Approved :: BSD License
Classifier: Programming Language :: Python :: 3
Classifier: Programming Language :: Python :: 3.8
Classifier: Programming Language :: Python :: 3.9
Classifier: Programming Language :: Python :: 3.10
Classifier: Programming Language :: Python :: 3.11
Classifier: Programming Language :: Python :: 3.12
Requires-Dist: PyJWT[crypto] (>=2.8.0,<3.0.0)
Requires-Dist: aiocache (>=0.12.2,<0.13.0)
Requires-Dist: aiohttp[speedups] (>=3.10.1,<4.0.0)
Requires-Dist: cachetools (>=5.3.2,<6.0.0)
Project-URL: Repository, https://github.com/ioxiocom/pyjwt-key-fetcher
